{
  "categories": [
    {
      "title": "Prayer & Synagogue",
      "packages": [
        "com.siddur.smart",
        "com.RustyBrick.Siddur",
        "com.kakatua.minyan"
      ]
    },
    {
      "title": "Torah & Daily Study",
      "packages": [
        "org.artscroll.digital",
        "com.mercava.mercava",
        "org.torah.is",
        "com.rambamapp.android",
        "org.chabad.dailystudy",
        "com.dafyomi"
      ]
    },
    {
      "title": "Jewish Life & Utilities",
      "packages": [
        "com.rustybrick.zmanim",
        "com.hebcal.hebcal",
        "org.israelcalendar.zmanim",
        "com.ou.kosher",
        "com.crcweb.Kashrus"
      ]
    },
    {
      "title": "News & Media",
      "packages": [
        "com.timesofisrael.online",
        "com.jpost.android",
        "com.jewishmusic.network"
      ]
    }
  ]
}
